<?xml version="1.0" encoding="UTF-8"?><?xml-stylesheet type='text/xsl' href='_UpgradeReport_Files/UpgradeReport.xslt'?><UpgradeLog>
<Properties><Property Name="Solution" Value="DrainageAnalysis">
</Property><Property Name="Solution File" Value="D:\Work\scientific research\PhD Research\Paper prepare\DrainageExtractionPaper\Paper_henan\DrainageAnalysis_PaperTest\DrainageAnalysis.sln">
</Property><Property Name="Date" Value="April-13-13">
</Property><Property Name="Time" Value="22:26 PM">
</Property></Properties><Event ErrorLevel="0" Project="" Source="DrainageAnalysis.sln" Description="Solution converted successfully">
</Event><Event ErrorLevel="3" Project="" Source="DrainageAnalysis.sln" Description="Converted">
</Event></UpgradeLog>